nextcodecli/VERSION
nextcodecli/__init__.py
nextcodecli/__main__.py
nextcodecli/commands/__init__.py
nextcodecli/commands/csa.py
nextcodecli/commands/keycloak.py
nextcodecli/commands/login.py
nextcodecli/commands/pipelines/__init__.py
nextcodecli/commands/pipelines/instance.py
nextcodecli/commands/pipelines/job.py
nextcodecli/commands/pipelines/jobs.py
nextcodecli/commands/pipelines/list.py
nextcodecli/commands/pipelines/run.py
nextcodecli/commands/pipelines/status.py
nextcodecli/commands/profile.py
nextcodecli/commands/project/__init__.py
nextcodecli/commands/project/fileaccess.py
nextcodecli/commands/project/status.py
nextcodecli/commands/project/users.py
nextcodecli/commands/query/__init__.py
nextcodecli/commands/query/run.py
nextcodecli/commands/query/status.py
nextcodecli/commands/query/templates.py
nextcodecli/commands/setproject.py
nextcodecli/commands/token.py
nextcodecli/commands/version.py
nextcodecli/commands/workflow/__init__.py
nextcodecli/commands/workflow/job.py
nextcodecli/commands/workflow/jobs.py
nextcodecli/commands/workflow/pipelines.py
nextcodecli/commands/workflow/projects.py
nextcodecli/commands/workflow/run.py
nextcodecli/commands/workflow/status.py
nextcodecli/csa_import.py
nextcodecli/pipelines/__init__.py
nextcodecli/pipelines/cmdutils.py
nextcodecli/pipelines/jobs.py
nextcodecli/pipelines/plot.py
nextcodecli/queryapi.py
nextcodecli/utils.py
nextcodecli/workflow/__init__.py
nextcodecli/workflow/cmdutils.py
nextcode_cli-3.1.1.dist-info/METADATA
nextcode_cli-3.1.1.dist-info/WHEEL
nextcode_cli-3.1.1.dist-info/entry_points.txt
nextcode_cli-3.1.1.dist-info/RECORD
