Metadata-Version: 2.3
Name: nextcode-cli
Version: 3.1.1
Summary: WuXi Nextcode commandline utilities
License: MIT
Author: WUXI NextCODE
Author-email: support@wuxinextcode.com
Maintainer: Genuity Science Software Development
Maintainer-email: sdev@genuitysci.com
Requires-Python: >=3.8,<4.0
Classifier: License :: OSI Approved :: MIT License
Classifier: Programming Language :: Python :: 3
Classifier: Programming Language :: Python :: 3.8
Classifier: Programming Language :: Python :: 3.9
Classifier: Programming Language :: Python :: 3.10
Classifier: Programming Language :: Python :: 3.11
Classifier: Programming Language :: Python :: 3.12
Classifier: Programming Language :: Python :: 3.13
Requires-Dist: click (>=8.1.3,<9.0.0)
Requires-Dist: hjson (>=3.1.0,<4.0.0)
Requires-Dist: jsonpath-rw (>=1.4.0,<2.0.0)
Requires-Dist: nextcode-sdk (>=2.1.1,<3.0.0)
Requires-Dist: python-dateutil (>=2.8.2,<3.0.0)
Requires-Dist: pyyaml (>=6.0,<7.0)
Requires-Dist: requests (>=2.28.2,<3.0.0)
Requires-Dist: tabulate (>=0.9.0,<0.10.0)
Project-URL: Homepage, https://www.wuxinextcode.com
